KeyMojiAPI/KeyMojiAPI.py
KeyMojiAPI/__init__.py
KeyMojiAPI/jf-openhuninn-1.1.ttf
KeyMojiAPI/sense8_null.png
KeyMojiAPI/sense_watermark.png
KeyMojiAPI-1.0.5.dist-info/LICENSE
KeyMojiAPI-1.0.5.dist-info/METADATA
KeyMojiAPI-1.0.5.dist-info/WHEEL
KeyMojiAPI-1.0.5.dist-info/top_level.txt
KeyMojiAPI-1.0.5.dist-info/RECORD
