Metadata-Version: 2.1
Name: KeyMojiAPI
Version: 1.0.5
Summary: KeyMoji sentimental analysis system differs from other "amature-tagged" and "pure-ML/DL" text sentimental analysis solutions in many ways. KeyMoji combines "syntactic structure information", "formal semantics" and "lexical semantic model" in one calculating process to estimate the sentimental bias and distributions of sentiments in texts.
Home-page: https://github.com/Droidtown/KeyMojiAPI
Author: Droidtown Linguistic Tech. Co. Ltd.
Author-email: info@droidtown.co
License: MIT License
Project-URL: Documentation, https://api.droidtown.co/KeyMojiAPI/document/
Project-URL: Source, https://github.com/Droidtown/KeyMojiAPI
Keywords: emotion,emotion recognition,emotions in formula,sentimentsentiment analyzer,sentiment analysis,sentiment detection,NLP,NLU,AI,artificial intelligence,computational linguistics,language,linguistics,natural language,natural language processing,natural language understanding,parsing,syntax,text analytics
Classifier: Programming Language :: Python :: 3
Classifier: Programming Language :: Python :: 3 :: Only
Classifier: Programming Language :: Python :: 3.6
Classifier: Programming Language :: Python :: 3.7
Classifier: Programming Language :: Python :: 3.8
Classifier: Programming Language :: Python :: 3.9
Classifier: License :: OSI Approved :: MIT License
Classifier: Operating System :: OS Independent
Classifier: Development Status :: 5 - Production/Stable
Classifier: Intended Audience :: Developers
Classifier: Intended Audience :: Customer Service
Classifier: Intended Audience :: Information Technology
Classifier: Natural Language :: Chinese (Traditional)
Classifier: Topic :: Software Development :: Libraries :: Python Modules
Classifier: Topic :: Text Processing
Classifier: Topic :: Text Processing :: Linguistic
Classifier: Topic :: Text Processing :: Filters
Classifier: Topic :: Utilities
Requires-Python: >=3.6.1
License-File: LICENSE
Requires-Dist: requests (>=2.25.1)
Requires-Dist: python-rapidjson (>=0.9.4)
Requires-Dist: matplotlib (>=3.3.3)
Requires-Dist: numpy (>=1.19.5)
Requires-Dist: scipy (>=1.5.4)
